{"category": "local", "body": "<p>Best youth project developed at the GovHack Logan event.</p>\n\n<h1>Prize</h1>\n\n<p>Cash up to the value of $500</p>\n\n<h1>Eligibility Criteria</h1>\n\n<p>Must be a participant at GovHack Logan and at least one team member under 18 years.</p>\n", "name": "Best of Logan - Youth", "title": "Best of Logan - Youth", "organisation": "logan-city-council", "jurisdiction": "qld", "portal_url": "http://portal.govhack.org/prizes/2016/qld/qld-best-of-logan---youth.html", "id": "qld-best-of-logan---youth", "organisation_title": "Logan City Council", "type": "Best In", "events": ["logan"], "projects": ["dont-crash", "accident-tracker"]}