{"category": "state", "body": "<p>Most Disruptive Innovation</p>\n\n<h1>Prize</h1>\n\n<p>Cash prize(s) up to the value of $500</p>\n\n<h1>Eligibility Criteria</h1>\n\n<p>The project that seems to have the most disruptive potential.</p>\n", "name": "Most Disruptive Innovation", "title": "Most Disruptive Innovation", "jurisdiction": "tas", "portal_url": "http://portal.govhack.org/prizes/2016/tas/tas-most-disruptive-innovation.html", "organisation_title": "ACS", "type": "Theme", "id": "tas-most-disruptive-innovation", "projects": ["binthere", "mission:-attrition", "smarter-training", "beat-the-press", "payparking.online"]}